google_selenium_bookname_fetcher/__init__.py
google_selenium_bookname_fetcher/main.py
google_selenium_bookname_fetcher-0.4.0.dist-info/METADATA
google_selenium_bookname_fetcher-0.4.0.dist-info/WHEEL
google_selenium_bookname_fetcher-0.4.0.dist-info/RECORD
